{"primaryContentSections":[{"kind":"declarations","declarations":[{"tokens":[{"kind":"attribute","text":"@discardableResult"},{"kind":"text","text":" "},{"kind":"keyword","text":"func"},{"kind":"text","text":" "},{"kind":"identifier","text":"sizeToFitAndMask"},{"kind":"text","text":"("},{"kind":"externalParam","text":"mode"},{"kind":"text","text":": "},{"kind":"typeIdentifier","identifier":"doc:\/\/com.davidbjames.C3\/documentation\/C3\/ExtendedImageMode","preciseIdentifier":"s:2C317ExtendedImageModeO","text":"ExtendedImageMode"},{"kind":"text","text":", "},{"kind":"externalParam","text":"outset"},{"kind":"text","text":" "},{"kind":"internalParam","text":"inset"},{"kind":"text","text":": "},{"kind":"typeIdentifier","identifier":"doc:\/\/com.davidbjames.C3\/documentation\/C3\/InsetGroup","preciseIdentifier":"s:2C310InsetGroupV","text":"InsetGroup"},{"kind":"text","text":"? = nil, "},{"kind":"externalParam","text":"axis"},{"kind":"text","text":": "},{"kind":"typeIdentifier","identifier":"doc:\/\/com.davidbjames.C3\/documentation\/C3\/Layout","preciseIdentifier":"s:2C36LayoutV","text":"Layout"},{"kind":"text","text":"."},{"kind":"typeIdentifier","identifier":"doc:\/\/com.davidbjames.C3\/documentation\/C3\/Layout\/Axis","preciseIdentifier":"s:2C36LayoutV4AxisO","text":"Axis"},{"kind":"text","text":" = .both, "},{"kind":"externalParam","text":"debug"},{"kind":"text","text":" "},{"kind":"internalParam","text":"debugImageMask"},{"kind":"text","text":": "},{"kind":"typeIdentifier","text":"Bool","preciseIdentifier":"s:Sb"},{"kind":"text","text":" = false, "},{"kind":"externalParam","text":"image"},{"kind":"text","text":" "},{"kind":"internalParam","text":"imageClosure"},{"kind":"text","text":": (("},{"kind":"typeIdentifier","identifier":"doc:\/\/com.davidbjames.C3\/documentation\/C3\/Mutator","preciseIdentifier":"s:2C37MutatorV","text":"Mutator"},{"kind":"text","text":"<"},{"kind":"typeIdentifier","text":"B","preciseIdentifier":"s:2C37MutatorVAASo11UIImageViewCRb_rlE1Bxmfp"},{"kind":"text","text":", "},{"kind":"typeIdentifier","text":"T","preciseIdentifier":"s:2C37MutatorVAASo11UIImageViewCRb_rlE1Tq_mfp"},{"kind":"text","text":">) -> "},{"kind":"typeIdentifier","text":"Void","preciseIdentifier":"s:s4Voida"},{"kind":"text","text":")? = nil) -> "},{"kind":"typeIdentifier","identifier":"doc:\/\/com.davidbjames.C3\/documentation\/C3\/Mutator","preciseIdentifier":"s:2C37MutatorV","text":"Mutator"},{"kind":"text","text":"<"},{"kind":"typeIdentifier","text":"B","preciseIdentifier":"s:2C37MutatorVAASo11UIImageViewCRb_rlE1Bxmfp"},{"kind":"text","text":", "},{"kind":"typeIdentifier","identifier":"doc:\/\/com.davidbjames.C3\/documentation\/C3\/ImageContainer","preciseIdentifier":"c:@M@C3@objc(cs)ImageContainer","text":"ImageContainer"},{"kind":"text","text":">"}],"languages":["swift"],"platforms":["iOS"]}]}],"schemaVersion":{"major":0,"minor":2,"patch":0},"sections":[],"variants":[{"paths":["\/documentation\/c3\/mutator\/sizetofitandmask(mode:outset:axis:debug:image:)"],"traits":[{"interfaceLanguage":"swift"}]}],"identifier":{"url":"doc:\/\/com.davidbjames.C3\/documentation\/C3\/Mutator\/sizeToFitAndMask(mode:outset:axis:debug:image:)","interfaceLanguage":"swift"},"abstract":[{"type":"text","text":"Size the image view(s) using the provided image "},{"type":"codeVoice","code":"mode"},{"type":"text","text":" "},{"type":"text","text":"on one or both axes such that the "},{"type":"emphasis","inlineContent":[{"type":"text","text":"rendered"}]},{"type":"text","text":" image size"},{"type":"text","text":" "},{"type":"text","text":"will match the "},{"type":"emphasis","inlineContent":[{"type":"text","text":"view"}]},{"type":"text","text":" size (without affecting the original"},{"type":"text","text":" "},{"type":"text","text":"image size), embed the image(s) in masking view(s)"},{"type":"text","text":" "},{"type":"text","text":"(ImageMask) that are sized to the image size and finally,"},{"type":"text","text":" "},{"type":"text","text":"embed the masks in a container (ImageContainer) that can"},{"type":"text","text":" "},{"type":"text","text":"be positioned or mutated (including borders) separately"},{"type":"text","text":" "},{"type":"text","text":"from the masked image."},{"type":"text","text":" "},{"type":"text","text":"This will pin the edges (on the provided axes) to the parent"},{"type":"text","text":" "},{"type":"text","text":"or reference."},{"type":"text","text":" "},{"type":"text","text":"Image mode "},{"type":"codeVoice","code":"fit"},{"type":"text","text":" will "},{"type":"emphasis","inlineContent":[{"type":"text","text":"shrink"}]},{"type":"text","text":" the image on one axis"},{"type":"text","text":" "},{"type":"text","text":"to match the original "},{"type":"emphasis","inlineContent":[{"type":"text","text":"image"}]},{"type":"text","text":" aspect ratio."},{"type":"text","text":" "},{"type":"text","text":"Image mode "},{"type":"codeVoice","code":"fill"},{"type":"text","text":" will "},{"type":"emphasis","inlineContent":[{"type":"text","text":"grow"}]},{"type":"text","text":" the image "},{"type":"emphasis","inlineContent":[{"type":"text","text":"view"}]},{"type":"text","text":" on one axis"},{"type":"text","text":" "},{"type":"text","text":"to match the original "},{"type":"emphasis","inlineContent":[{"type":"text","text":"image"}]},{"type":"text","text":" aspect ratio."},{"type":"text","text":" "},{"type":"text","text":"Image mode "},{"type":"codeVoice","code":"clipped"},{"type":"text","text":" will "},{"type":"emphasis","inlineContent":[{"type":"text","text":"grow"}]},{"type":"text","text":" the image "},{"type":"emphasis","inlineContent":[{"type":"text","text":"view"}]},{"type":"text","text":" on one axis"},{"type":"text","text":" "},{"type":"text","text":"to match the original "},{"type":"emphasis","inlineContent":[{"type":"text","text":"image"}]},{"type":"text","text":" aspect ratio and then"},{"type":"text","text":" "},{"type":"text","text":"clip the image (aka mask) to the parent view or guide."},{"type":"text","text":" "},{"type":"text","text":"Image mode "},{"type":"codeVoice","code":"stretch"},{"type":"text","text":" will leave the image "},{"type":"emphasis","inlineContent":[{"type":"text","text":"view"}]},{"type":"text","text":" size,"},{"type":"text","text":" "},{"type":"text","text":"disregarding the aspect ratio of the image, such that"},{"type":"text","text":" "},{"type":"text","text":"the rendered "},{"type":"emphasis","inlineContent":[{"type":"text","text":"image"}]},{"type":"text","text":" will be stretched to fit, and"},{"type":"text","text":" "},{"type":"text","text":"therefore could be distorted."},{"type":"text","text":" "},{"type":"text","text":"See ImageMode documentation for more information\/examples."},{"type":"text","text":" "},{"type":"text","text":"Provide "},{"type":"codeVoice","code":"outset"},{"type":"text","text":" on any edge to simultaneously grow the"},{"type":"text","text":" "},{"type":"text","text":"image beyond the edge(s) and shrink the masking view(s)"},{"type":"text","text":" "},{"type":"text","text":"by the same amount on those edge(s), effectively expanding"},{"type":"text","text":" "},{"type":"text","text":"the image and then masking out the outer area."},{"type":"text","text":" "},{"type":"text","text":"Tweaking which edges are outset and the degree of the outset"},{"type":"text","text":" "},{"type":"text","text":"will ensure the desired part of the image(s) are revealed."},{"type":"text","text":" "},{"type":"text","text":"To further control how the image(s) are positioned within"},{"type":"text","text":" "},{"type":"text","text":"the mask, provide the trailing "},{"type":"codeVoice","code":"image"},{"type":"text","text":" closure and position"},{"type":"text","text":" "},{"type":"text","text":"the image(s) there."},{"type":"text","text":" "},{"type":"text","text":"To use a custom image mask (e.g. a shape) follow this method"},{"type":"text","text":" "},{"type":"text","text":"call with a call to "},{"type":"codeVoice","code":"mask()"},{"type":"text","text":" or "},{"type":"codeVoice","code":"reveal()"},{"type":"text","text":"."},{"type":"text","text":" "},{"type":"text","text":"For more advanced masking see Mutator "},{"type":"codeVoice","code":"embedMaskedView()"},{"type":"text","text":"."},{"type":"text","text":" "},{"type":"text","text":"Simple and advanced examples: https:\/\/a.cl.ly\/8Lun2oKb"},{"type":"text","text":" "},{"type":"text","text":"See also "},{"type":"codeVoice","code":"sizeToWidthAndMask()"},{"type":"text","text":" and "},{"type":"codeVoice","code":"sizeToHeightAndMask()"},{"type":"text","text":" "},{"type":"text","text":"methods which support percentage-based sizes on a single axis"},{"type":"text","text":" "},{"type":"text","text":"(for typical aspect image sizing)."},{"type":"text","text":" "},{"type":"text","text":"To debug image and mask size and position pass "},{"type":"codeVoice","code":"debug"},{"type":"text","text":"."},{"type":"text","text":" "},{"type":"text","text":"See also https:\/\/a.cl.ly\/5zud8Y7q"}],"kind":"symbol","metadata":{"conformance":{"constraints":[{"type":"codeVoice","code":"B"},{"type":"text","text":" conforms to "},{"type":"codeVoice","code":"Queryable"},{"type":"text","text":" and "},{"type":"codeVoice","code":"T"},{"type":"text","text":" inherits "},{"type":"codeVoice","code":"UIImageView"},{"type":"text","text":"."}],"availabilityPrefix":[{"type":"text","text":"Available when"}],"conformancePrefix":[{"type":"text","text":"Conforms when"}]},"role":"symbol","title":"sizeToFitAndMask(mode:outset:axis:debug:image:)","roleHeading":"Instance Method","fragments":[{"kind":"keyword","text":"func"},{"kind":"text","text":" "},{"kind":"identifier","text":"sizeToFitAndMask"},{"kind":"text","text":"("},{"kind":"externalParam","text":"mode"},{"kind":"text","text":": "},{"kind":"typeIdentifier","text":"ExtendedImageMode","preciseIdentifier":"s:2C317ExtendedImageModeO"},{"kind":"text","text":", "},{"kind":"externalParam","text":"outset"},{"kind":"text","text":": "},{"kind":"typeIdentifier","text":"InsetGroup","preciseIdentifier":"s:2C310InsetGroupV"},{"kind":"text","text":"?, "},{"kind":"externalParam","text":"axis"},{"kind":"text","text":": "},{"kind":"typeIdentifier","text":"Layout","preciseIdentifier":"s:2C36LayoutV"},{"kind":"text","text":"."},{"kind":"typeIdentifier","text":"Axis","preciseIdentifier":"s:2C36LayoutV4AxisO"},{"kind":"text","text":", "},{"kind":"externalParam","text":"debug"},{"kind":"text","text":": "},{"kind":"typeIdentifier","text":"Bool","preciseIdentifier":"s:Sb"},{"kind":"text","text":", "},{"kind":"externalParam","text":"image"},{"kind":"text","text":": (("},{"kind":"typeIdentifier","text":"Mutator","preciseIdentifier":"s:2C37MutatorV"},{"kind":"text","text":"<"},{"kind":"typeIdentifier","text":"B","preciseIdentifier":"s:2C37MutatorVAASo11UIImageViewCRb_rlE1Bxmfp"},{"kind":"text","text":", "},{"kind":"typeIdentifier","text":"T","preciseIdentifier":"s:2C37MutatorVAASo11UIImageViewCRb_rlE1Tq_mfp"},{"kind":"text","text":">) -> "},{"kind":"typeIdentifier","text":"Void","preciseIdentifier":"s:s4Voida"},{"kind":"text","text":")?) -> "},{"kind":"typeIdentifier","text":"Mutator","preciseIdentifier":"s:2C37MutatorV"},{"kind":"text","text":"<"},{"kind":"typeIdentifier","text":"B","preciseIdentifier":"s:2C37MutatorVAASo11UIImageViewCRb_rlE1Bxmfp"},{"kind":"text","text":", "},{"kind":"typeIdentifier","text":"ImageContainer","preciseIdentifier":"c:@M@C3@objc(cs)ImageContainer"},{"kind":"text","text":">"}],"symbolKind":"method","externalID":"s:2C37MutatorVAASo11UIImageViewCRb_rlE16sizeToFitAndMask4mode6outset4axis5debug5imageACyxAA14ImageContainerCGAA08ExtendedO4ModeO_AA10InsetGroupVSgAA6LayoutV4AxisOSbyACyxq_GcSgtF","extendedModule":"C3","modules":[{"name":"C3"}]},"hierarchy":{"paths":[["doc:\/\/com.davidbjames.C3\/documentation\/C3","doc:\/\/com.davidbjames.C3\/documentation\/C3\/Mutator"]]},"references":{"doc://com.davidbjames.C3/documentation/C3/ExtendedImageMode":{"role":"symbol","title":"ExtendedImageMode","fragments":[{"kind":"keyword","text":"enum"},{"kind":"text","text":" "},{"kind":"identifier","text":"ExtendedImageMode"}],"abstract":[{"type":"text","text":"Extended image modes for use with masking"}],"identifier":"doc:\/\/com.davidbjames.C3\/documentation\/C3\/ExtendedImageMode","kind":"symbol","type":"topic","navigatorTitle":[{"kind":"identifier","text":"ExtendedImageMode"}],"url":"\/documentation\/c3\/extendedimagemode"},"doc://com.davidbjames.C3/documentation/C3/ImageContainer":{"role":"symbol","title":"ImageContainer","fragments":[{"kind":"keyword","text":"class"},{"kind":"text","text":" "},{"kind":"identifier","text":"ImageContainer"}],"abstract":[{"type":"text","text":"Special embedded view type that is returned"},{"type":"text","text":" "},{"type":"text","text":"from Mutator.sizeToFitAndMask() that contains"},{"type":"text","text":" "},{"type":"text","text":"an ImageMask (and image)."},{"type":"text","text":" "},{"type":"text","text":"This type is not meant to be instantiated"},{"type":"text","text":" "},{"type":"text","text":"outside of the sizeToFitAndMask() API."}],"identifier":"doc:\/\/com.davidbjames.C3\/documentation\/C3\/ImageContainer","kind":"symbol","type":"topic","navigatorTitle":[{"kind":"identifier","text":"ImageContainer"}],"url":"\/documentation\/c3\/imagecontainer"},"doc://com.davidbjames.C3/documentation/C3":{"role":"collection","title":"C3","abstract":[{"type":"strong","inlineContent":[{"type":"text","text":"C3UI"}]},{"type":"text","text":" is a Swift framework for developing apps on iOS and iPadOS."}],"identifier":"doc:\/\/com.davidbjames.C3\/documentation\/C3","kind":"symbol","type":"topic","url":"\/documentation\/c3"},"doc://com.davidbjames.C3/documentation/C3/Layout/Axis":{"role":"symbol","title":"Layout.Axis","fragments":[{"kind":"keyword","text":"enum"},{"kind":"text","text":" "},{"kind":"identifier","text":"Axis"}],"abstract":[{"type":"text","text":"The axis or axes of layout."}],"identifier":"doc:\/\/com.davidbjames.C3\/documentation\/C3\/Layout\/Axis","kind":"symbol","type":"topic","navigatorTitle":[{"kind":"identifier","text":"Axis"}],"url":"\/documentation\/c3\/layout\/axis"},"doc://com.davidbjames.C3/documentation/C3/Query":{"role":"symbol","title":"Query","fragments":[{"kind":"keyword","text":"struct"},{"kind":"text","text":" "},{"kind":"identifier","text":"Query"}],"abstract":[{"type":"text","text":"Core "},{"type":"codeVoice","code":"Query"},{"type":"text","text":" wrapper to one or more items of "},{"type":"reference","isActive":true,"identifier":"doc:\/\/com.davidbjames.C3\/documentation\/C3\/Queryable"},{"type":"text","text":" type."}],"identifier":"doc:\/\/com.davidbjames.C3\/documentation\/C3\/Query","kind":"symbol","type":"topic","navigatorTitle":[{"kind":"identifier","text":"Query"}],"url":"\/documentation\/c3\/query"},"doc://com.davidbjames.C3/documentation/C3/Mutator":{"role":"symbol","title":"Mutator","fragments":[{"kind":"keyword","text":"struct"},{"kind":"text","text":" "},{"kind":"identifier","text":"Mutator"}],"abstract":[{"type":"text","text":"This wraps the "},{"type":"reference","isActive":true,"identifier":"doc:\/\/com.davidbjames.C3\/documentation\/C3\/Query"},{"type":"text","text":" object that holds the items to"},{"type":"text","text":" "},{"type":"text","text":"be mutated and also conforms to the "},{"type":"reference","isActive":true,"identifier":"doc:\/\/com.davidbjames.C3\/documentation\/C3\/QueryInterface"},{"type":"text","text":" "},{"type":"text","text":"suite of protocols for common functionality."}],"identifier":"doc:\/\/com.davidbjames.C3\/documentation\/C3\/Mutator","kind":"symbol","type":"topic","navigatorTitle":[{"kind":"identifier","text":"Mutator"}],"url":"\/documentation\/c3\/mutator"},"doc://com.davidbjames.C3/documentation/C3/Mutator/sizeToFitAndMask(mode:outset:axis:debug:image:)":{"conformance":{"constraints":[{"type":"codeVoice","code":"B"},{"type":"text","text":" conforms to "},{"type":"codeVoice","code":"Queryable"},{"type":"text","text":" and "},{"type":"codeVoice","code":"T"},{"type":"text","text":" inherits "},{"type":"codeVoice","code":"UIImageView"},{"type":"text","text":"."}],"availabilityPrefix":[{"type":"text","text":"Available when"}],"conformancePrefix":[{"type":"text","text":"Conforms when"}]},"role":"symbol","title":"sizeToFitAndMask(mode:outset:axis:debug:image:)","fragments":[{"kind":"keyword","text":"func"},{"kind":"text","text":" "},{"kind":"identifier","text":"sizeToFitAndMask"},{"kind":"text","text":"("},{"kind":"externalParam","text":"mode"},{"kind":"text","text":": "},{"kind":"typeIdentifier","text":"ExtendedImageMode","preciseIdentifier":"s:2C317ExtendedImageModeO"},{"kind":"text","text":", "},{"kind":"externalParam","text":"outset"},{"kind":"text","text":": "},{"kind":"typeIdentifier","text":"InsetGroup","preciseIdentifier":"s:2C310InsetGroupV"},{"kind":"text","text":"?, "},{"kind":"externalParam","text":"axis"},{"kind":"text","text":": "},{"kind":"typeIdentifier","text":"Layout","preciseIdentifier":"s:2C36LayoutV"},{"kind":"text","text":"."},{"kind":"typeIdentifier","text":"Axis","preciseIdentifier":"s:2C36LayoutV4AxisO"},{"kind":"text","text":", "},{"kind":"externalParam","text":"debug"},{"kind":"text","text":": "},{"kind":"typeIdentifier","text":"Bool","preciseIdentifier":"s:Sb"},{"kind":"text","text":", "},{"kind":"externalParam","text":"image"},{"kind":"text","text":": (("},{"kind":"typeIdentifier","text":"Mutator","preciseIdentifier":"s:2C37MutatorV"},{"kind":"text","text":"<"},{"kind":"typeIdentifier","text":"B","preciseIdentifier":"s:2C37MutatorVAASo11UIImageViewCRb_rlE1Bxmfp"},{"kind":"text","text":", "},{"kind":"typeIdentifier","text":"T","preciseIdentifier":"s:2C37MutatorVAASo11UIImageViewCRb_rlE1Tq_mfp"},{"kind":"text","text":">) -> "},{"kind":"typeIdentifier","text":"Void","preciseIdentifier":"s:s4Voida"},{"kind":"text","text":")?) -> "},{"kind":"typeIdentifier","text":"Mutator","preciseIdentifier":"s:2C37MutatorV"},{"kind":"text","text":"<"},{"kind":"typeIdentifier","text":"B","preciseIdentifier":"s:2C37MutatorVAASo11UIImageViewCRb_rlE1Bxmfp"},{"kind":"text","text":", "},{"kind":"typeIdentifier","text":"ImageContainer","preciseIdentifier":"c:@M@C3@objc(cs)ImageContainer"},{"kind":"text","text":">"}],"abstract":[{"type":"text","text":"Size the image view(s) using the provided image "},{"type":"codeVoice","code":"mode"},{"type":"text","text":" "},{"type":"text","text":"on one or both axes such that the "},{"type":"emphasis","inlineContent":[{"type":"text","text":"rendered"}]},{"type":"text","text":" image size"},{"type":"text","text":" "},{"type":"text","text":"will match the "},{"type":"emphasis","inlineContent":[{"type":"text","text":"view"}]},{"type":"text","text":" size (without affecting the original"},{"type":"text","text":" "},{"type":"text","text":"image size), embed the image(s) in masking view(s)"},{"type":"text","text":" "},{"type":"text","text":"(ImageMask) that are sized to the image size and finally,"},{"type":"text","text":" "},{"type":"text","text":"embed the masks in a container (ImageContainer) that can"},{"type":"text","text":" "},{"type":"text","text":"be positioned or mutated (including borders) separately"},{"type":"text","text":" "},{"type":"text","text":"from the masked image."},{"type":"text","text":" "},{"type":"text","text":"This will pin the edges (on the provided axes) to the parent"},{"type":"text","text":" "},{"type":"text","text":"or reference."},{"type":"text","text":" "},{"type":"text","text":"Image mode "},{"type":"codeVoice","code":"fit"},{"type":"text","text":" will "},{"type":"emphasis","inlineContent":[{"type":"text","text":"shrink"}]},{"type":"text","text":" the image on one axis"},{"type":"text","text":" "},{"type":"text","text":"to match the original "},{"type":"emphasis","inlineContent":[{"type":"text","text":"image"}]},{"type":"text","text":" aspect ratio."},{"type":"text","text":" "},{"type":"text","text":"Image mode "},{"type":"codeVoice","code":"fill"},{"type":"text","text":" will "},{"type":"emphasis","inlineContent":[{"type":"text","text":"grow"}]},{"type":"text","text":" the image "},{"type":"emphasis","inlineContent":[{"type":"text","text":"view"}]},{"type":"text","text":" on one axis"},{"type":"text","text":" "},{"type":"text","text":"to match the original "},{"type":"emphasis","inlineContent":[{"type":"text","text":"image"}]},{"type":"text","text":" aspect ratio."},{"type":"text","text":" "},{"type":"text","text":"Image mode "},{"type":"codeVoice","code":"clipped"},{"type":"text","text":" will "},{"type":"emphasis","inlineContent":[{"type":"text","text":"grow"}]},{"type":"text","text":" the image "},{"type":"emphasis","inlineContent":[{"type":"text","text":"view"}]},{"type":"text","text":" on one axis"},{"type":"text","text":" "},{"type":"text","text":"to match the original "},{"type":"emphasis","inlineContent":[{"type":"text","text":"image"}]},{"type":"text","text":" aspect ratio and then"},{"type":"text","text":" "},{"type":"text","text":"clip the image (aka mask) to the parent view or guide."},{"type":"text","text":" "},{"type":"text","text":"Image mode "},{"type":"codeVoice","code":"stretch"},{"type":"text","text":" will leave the image "},{"type":"emphasis","inlineContent":[{"type":"text","text":"view"}]},{"type":"text","text":" size,"},{"type":"text","text":" "},{"type":"text","text":"disregarding the aspect ratio of the image, such that"},{"type":"text","text":" "},{"type":"text","text":"the rendered "},{"type":"emphasis","inlineContent":[{"type":"text","text":"image"}]},{"type":"text","text":" will be stretched to fit, and"},{"type":"text","text":" "},{"type":"text","text":"therefore could be distorted."},{"type":"text","text":" "},{"type":"text","text":"See ImageMode documentation for more information\/examples."},{"type":"text","text":" "},{"type":"text","text":"Provide "},{"type":"codeVoice","code":"outset"},{"type":"text","text":" on any edge to simultaneously grow the"},{"type":"text","text":" "},{"type":"text","text":"image beyond the edge(s) and shrink the masking view(s)"},{"type":"text","text":" "},{"type":"text","text":"by the same amount on those edge(s), effectively expanding"},{"type":"text","text":" "},{"type":"text","text":"the image and then masking out the outer area."},{"type":"text","text":" "},{"type":"text","text":"Tweaking which edges are outset and the degree of the outset"},{"type":"text","text":" "},{"type":"text","text":"will ensure the desired part of the image(s) are revealed."},{"type":"text","text":" "},{"type":"text","text":"To further control how the image(s) are positioned within"},{"type":"text","text":" "},{"type":"text","text":"the mask, provide the trailing "},{"type":"codeVoice","code":"image"},{"type":"text","text":" closure and position"},{"type":"text","text":" "},{"type":"text","text":"the image(s) there."},{"type":"text","text":" "},{"type":"text","text":"To use a custom image mask (e.g. a shape) follow this method"},{"type":"text","text":" "},{"type":"text","text":"call with a call to "},{"type":"codeVoice","code":"mask()"},{"type":"text","text":" or "},{"type":"codeVoice","code":"reveal()"},{"type":"text","text":"."},{"type":"text","text":" "},{"type":"text","text":"For more advanced masking see Mutator "},{"type":"codeVoice","code":"embedMaskedView()"},{"type":"text","text":"."},{"type":"text","text":" "},{"type":"text","text":"Simple and advanced examples: https:\/\/a.cl.ly\/8Lun2oKb"},{"type":"text","text":" "},{"type":"text","text":"See also "},{"type":"codeVoice","code":"sizeToWidthAndMask()"},{"type":"text","text":" and "},{"type":"codeVoice","code":"sizeToHeightAndMask()"},{"type":"text","text":" "},{"type":"text","text":"methods which support percentage-based sizes on a single axis"},{"type":"text","text":" "},{"type":"text","text":"(for typical aspect image sizing)."},{"type":"text","text":" "},{"type":"text","text":"To debug image and mask size and position pass "},{"type":"codeVoice","code":"debug"},{"type":"text","text":"."},{"type":"text","text":" "},{"type":"text","text":"See also https:\/\/a.cl.ly\/5zud8Y7q"}],"identifier":"doc:\/\/com.davidbjames.C3\/documentation\/C3\/Mutator\/sizeToFitAndMask(mode:outset:axis:debug:image:)","kind":"symbol","type":"topic","url":"\/documentation\/c3\/mutator\/sizetofitandmask(mode:outset:axis:debug:image:)"},"doc://com.davidbjames.C3/documentation/C3/QueryInterface":{"role":"symbol","title":"QueryInterface","fragments":[{"kind":"keyword","text":"protocol"},{"kind":"text","text":" "},{"kind":"identifier","text":"QueryInterface"}],"abstract":[{"type":"text","text":"QueryInterface provides the common interface to"},{"type":"text","text":" "},{"type":"text","text":"queried items via "},{"type":"reference","isActive":true,"identifier":"doc:\/\/com.davidbjames.C3\/documentation\/C3\/Query"},{"type":"text","text":", "},{"type":"reference","isActive":true,"identifier":"doc:\/\/com.davidbjames.C3\/documentation\/C3\/Mutator"},{"type":"text","text":" and "},{"type":"codeVoice","code":"Autolayout"},{"type":"text","text":" wrappers."}],"identifier":"doc:\/\/com.davidbjames.C3\/documentation\/C3\/QueryInterface","kind":"symbol","type":"topic","navigatorTitle":[{"kind":"identifier","text":"QueryInterface"}],"url":"\/documentation\/c3\/queryinterface"},"doc://com.davidbjames.C3/documentation/C3/InsetGroup":{"role":"symbol","title":"InsetGroup","fragments":[{"kind":"keyword","text":"struct"},{"kind":"text","text":" "},{"kind":"identifier","text":"InsetGroup"}],"abstract":[{"type":"text","text":"Inset group of top, bottom, leading and trailing."}],"identifier":"doc:\/\/com.davidbjames.C3\/documentation\/C3\/InsetGroup","kind":"symbol","type":"topic","navigatorTitle":[{"kind":"identifier","text":"InsetGroup"}],"url":"\/documentation\/c3\/insetgroup"},"doc://com.davidbjames.C3/documentation/C3/Layout":{"role":"symbol","title":"Layout","fragments":[{"kind":"keyword","text":"struct"},{"kind":"text","text":" "},{"kind":"identifier","text":"Layout"}],"abstract":[{"type":"text","text":"Container for options and enumerations that are"},{"type":"text","text":" "},{"type":"text","text":"used for layout in this framework."}],"identifier":"doc:\/\/com.davidbjames.C3\/documentation\/C3\/Layout","kind":"symbol","type":"topic","navigatorTitle":[{"kind":"identifier","text":"Layout"}],"url":"\/documentation\/c3\/layout"}}}